rclog/__init__.py
rclog/config_log.py
rclog/env.py
rclog/exception.py
rclog/get_log.py
rclog/io.py
rclog/trans.py
rclog-1.4.0.dist-info/WHEEL
rclog-1.4.0.dist-info/METADATA
rclog-1.4.0.dist-info/RECORD
