Metadata-Version: 2.1
Name: rclog
Version: 1.4.0
Summary: A wrapper for the logging module in python.
License: MIT
Author-email: break-soul <rouc@rouc.net>
Requires-Python: >=3.8
Project-URL: Repository, https://github.com/break-soul/rclog
